Metadata-Version: 2.1
Name: setuptools-rust-bundled
Version: 0.1.0
Summary: Rust extension builder shipped with rust toolchain
Author-email: Yasuo Ozu <opensource@qunasys.com>
License: MIT
Keywords: setuptools,rust,build-backend
Classifier: Programming Language :: Python :: 3
Requires-Python: >=3.8
License-File: LICENSE
